MANIFEST.in
README.rst
setup.py
collective/__init__.py
collective.js.throttledebounce.egg-info/PKG-INFO
collective.js.throttledebounce.egg-info/SOURCES.txt
collective.js.throttledebounce.egg-info/dependency_links.txt
collective.js.throttledebounce.egg-info/entry_points.txt
collective.js.throttledebounce.egg-info/namespace_packages.txt
collective.js.throttledebounce.egg-info/not-zip-safe
collective.js.throttledebounce.egg-info/requires.txt
collective.js.throttledebounce.egg-info/top_level.txt
collective/js/__init__.py
collective/js/throttledebounce/__init__.py
collective/js/throttledebounce/configure.zcml
collective/js/throttledebounce/Extensions/__init__.py
collective/js/throttledebounce/Extensions/install.py
collective/js/throttledebounce/profiles/default/jsregistry.xml
collective/js/throttledebounce/profiles/default/metadata.xml
collective/js/throttledebounce/profiles/default_plone5/metadata.xml
collective/js/throttledebounce/profiles/default_plone5/registry.xml
collective/js/throttledebounce/profiles/uninstall/jsregistry.xml
collective/js/throttledebounce/profiles/uninstall_plone5/registry.xml
collective/js/throttledebounce/resources/main.js
collective/js/throttledebounce/resources/throttledebounce-compiled.js
collective/js/throttledebounce/resources/throttledebounce.js
collective/js/throttledebounce/tests/__init__.py
collective/js/throttledebounce/tests/test_uninstall.py
collective/js/throttledebounce/upgrades/__init__.py
collective/js/throttledebounce/upgrades/20191217181055_move_js_to_resource_folder_for_plone_4/__init__.py
collective/js/throttledebounce/upgrades/20191217181055_move_js_to_resource_folder_for_plone_4/jsregistry.xml
collective/js/throttledebounce/upgrades/20191217181055_move_js_to_resource_folder_for_plone_4/upgrade.py
collective/js/throttledebounce/upgrades/20191217181451_provide_compiled_resource_bundles_for_plone_5/__init__.py
collective/js/throttledebounce/upgrades/20191217181451_provide_compiled_resource_bundles_for_plone_5/registry.xml
collective/js/throttledebounce/upgrades/20191217181451_provide_compiled_resource_bundles_for_plone_5/upgrade.py
docs/HISTORY.txt