Metadata-Version: 2.1
Name: collective.js.throttledebounce
Version: 1.3.0
Summary: Installs the throttle / debounce plugin
Home-page: https://github.com/collective/collective.js.throttledebounce
Author: Jonas Baumann, 4teamwork GmbH
Author-email: mailto:info@4teamwork.ch
License: GPL2
Platform: UNKNOWN
Classifier: Programming Language :: Python
Classifier: Framework :: Plone
Classifier: Framework :: Plone :: 4.3
Classifier: Framework :: Plone :: 5.1
Provides-Extra: tests
